BOFS/BOFSFlask.py
BOFS/BOFSSession.py
BOFS/JSONQuestionnaire.py
BOFS/JSONTable.py
BOFS/PageList.py
BOFS/__init__.py
BOFS/__main__.py
BOFS/cli.py
BOFS/create_app.py
BOFS/globals.py
BOFS/init_wizard.py
BOFS/util.py
BOFS/__pycache__/BOFSFlask.cpython-311.pyc
BOFS/__pycache__/BOFSFlask.cpython-314.pyc
BOFS/__pycache__/BOFSFlask.cpython-38.pyc
BOFS/__pycache__/BOFSFlask.cpython-39.pyc
BOFS/__pycache__/BOFSSession.cpython-311.pyc
BOFS/__pycache__/BOFSSession.cpython-314.pyc
BOFS/__pycache__/BOFSSession.cpython-39.pyc
BOFS/__pycache__/JSONQuestionnaire.cpython-311.pyc
BOFS/__pycache__/JSONQuestionnaire.cpython-314.pyc
BOFS/__pycache__/JSONQuestionnaire.cpython-39.pyc
BOFS/__pycache__/JSONTable.cpython-311.pyc
BOFS/__pycache__/JSONTable.cpython-314.pyc
BOFS/__pycache__/JSONTable.cpython-39.pyc
BOFS/__pycache__/PageList.cpython-311.pyc
BOFS/__pycache__/PageList.cpython-314.pyc
BOFS/__pycache__/PageList.cpython-39.pyc
BOFS/__pycache__/__init__.cpython-311.pyc
BOFS/__pycache__/__init__.cpython-314.pyc
BOFS/__pycache__/__init__.cpython-38.pyc
BOFS/__pycache__/__init__.cpython-39.pyc
BOFS/__pycache__/__main__.cpython-311.pyc
BOFS/__pycache__/__main__.cpython-314.pyc
BOFS/__pycache__/__main__.cpython-39.pyc
BOFS/__pycache__/cli.cpython-311.pyc
BOFS/__pycache__/cli.cpython-314.pyc
BOFS/__pycache__/cli.cpython-39.pyc
BOFS/__pycache__/create_app.cpython-311.pyc
BOFS/__pycache__/create_app.cpython-314.pyc
BOFS/__pycache__/create_app.cpython-39.pyc
BOFS/__pycache__/globals.cpython-311.pyc
BOFS/__pycache__/globals.cpython-314.pyc
BOFS/__pycache__/globals.cpython-38.pyc
BOFS/__pycache__/globals.cpython-39.pyc
BOFS/__pycache__/init_wizard.cpython-314.pyc
BOFS/__pycache__/init_wizard.cpython-39.pyc
BOFS/__pycache__/util.cpython-311.pyc
BOFS/__pycache__/util.cpython-314.pyc
BOFS/__pycache__/util.cpython-38.pyc
BOFS/__pycache__/util.cpython-39.pyc
BOFS/admin/Results.py
BOFS/admin/SummaryStats.py
BOFS/admin/__init__.py
BOFS/admin/util.py
BOFS/admin/views.py
BOFS/bride_of_frankensystem.egg-info/PKG-INFO
BOFS/bride_of_frankensystem.egg-info/SOURCES.txt
BOFS/bride_of_frankensystem.egg-info/dependency_links.txt
BOFS/bride_of_frankensystem.egg-info/entry_points.txt
BOFS/bride_of_frankensystem.egg-info/requires.txt
BOFS/bride_of_frankensystem.egg-info/top_level.txt
bride_of_frankensystem-2.0.0.10.dist-info/licenses/LICENSE
bride_of_frankensystem-2.0.0.10.dist-info/IMPLEMENTATION_STATUS.md
bride_of_frankensystem-2.0.0.10.dist-info/METADATA
bride_of_frankensystem-2.0.0.10.dist-info/WHEEL
bride_of_frankensystem-2.0.0.10.dist-info/entry_points.txt
bride_of_frankensystem-2.0.0.10.dist-info/top_level.txt
bride_of_frankensystem-2.0.0.10.dist-info/RECORD
