Metadata-Version: 2.4
Name: bride-of-frankensystem
Version: 2.0.0.10
Summary: A framework that allows for the development of custom online experiments and surveys.
Author-email: Colby Johanson <colby.g.j@gmail.com>
License:                    GNU LESSER GENERAL PUBLIC LICENSE
Project-URL: Homepage, https://github.com/colbyj/bride-of-frankensystem/
Project-URL: Documentation, https://docs.frankensystem.net
Classifier: License :: OSI Approved :: GNU Lesser General Public License v3 (LGPLv3)
Classifier: Programming Language :: Python
Classifier: Programming Language :: Python :: 3
Classifier: Framework :: Flask
Requires-Python: >=3.9
License-File: LICENSE
Requires-Dist: flask>=2.3.0
Requires-Dist: eventlet
Requires-Dist: sqlalchemy>=1.4.18
Requires-Dist: flask-sqlalchemy>=3.0.0
Requires-Dist: flask-compress
Requires-Dist: toml
Requires-Dist: crawlerdetect
Requires-Dist: pandas
Requires-Dist: questionary>=2.1.0
Dynamic: license-file
